setup.py
FastHPOCR/HPOAnnotator.py
FastHPOCR/IndexHPO.py
FastHPOCR/IndexMONDO.py
FastHPOCR/IndexORPHANET.py
FastHPOCR/IndexSNOMED.py
FastHPOCR/README.md
FastHPOCR/__init__.py
FastHPOCR/license.txt
FastHPOCR.egg-info/PKG-INFO
FastHPOCR.egg-info/SOURCES.txt
FastHPOCR.egg-info/dependency_links.txt
FastHPOCR.egg-info/top_level.txt
FastHPOCR/cr/CRIndexKB.py
FastHPOCR/cr/CandidateMatcher.py
FastHPOCR/cr/FormatResults.py
FastHPOCR/cr/SequenceCache.py
FastHPOCR/cr/TextProcessor.py
FastHPOCR/cr/TextSplitter.py
FastHPOCR/cr/__init__.py
FastHPOCR/index/HPOLabelCollector.py
FastHPOCR/index/IndexTerms.py
FastHPOCR/index/LabelProcessor.py
FastHPOCR/index/MONDOLabelCollector.py
FastHPOCR/index/ORPHALabelCollector.py
FastHPOCR/index/PreprocessHPOTerms.py
FastHPOCR/index/PreprocessMONDOTerms.py
FastHPOCR/index/PreprocessORPHATerms.py
FastHPOCR/index/PreprocessSNOMEDTerms.py
FastHPOCR/index/SNOMEDLabelCollector.py
FastHPOCR/index/SNOMEDParser.py
FastHPOCR/index/SynonymExpader.py
FastHPOCR/index/__init__.py
FastHPOCR/resources/base-synonyms
FastHPOCR/resources/vocab.clusters.list
FastHPOCR/util/AnnotationObject.py
FastHPOCR/util/AnnotationToken.py
FastHPOCR/util/CRConstants.py
FastHPOCR/util/ConfigConstants.py
FastHPOCR/util/ContentUtil.py
FastHPOCR/util/OntoReader.py
FastHPOCR/util/SequenceData.py
FastHPOCR/util/__init__.py