Metadata-Version: 2.1
Name: FastHPOCR
Version: 0.1.4
Summary: FastHPOCR is a phenotype concept recognition package using the Human Phenotype Ontology to extract concepts from free text.
Author: Tudor Groza
